ros_cross_compile/__init__.py
ros_cross_compile/__main__.py
ros_cross_compile/builders.py
ros_cross_compile/data_collector.py
ros_cross_compile/dependencies.py
ros_cross_compile/docker_client.py
ros_cross_compile/pipeline_stages.py
ros_cross_compile/platform.py
ros_cross_compile/ros_cross_compile.py
ros_cross_compile/runtime.py
ros_cross_compile/sysroot_creator.py
ros_cross_compile/docker/build_workspace.sh
ros_cross_compile/docker/gather_rosdeps.sh
ros_cross_compile/docker/rosdep.Dockerfile
ros_cross_compile/docker/rosdep_focal.Dockerfile
ros_cross_compile/docker/runtime.Dockerfile
ros_cross_compile/docker/sysroot.Dockerfile
ros_cross_compile/mixins/cross-compile.mixin
ros_cross_compile/mixins/index.yaml
ros_cross_compile/qemu/qemu-aarch64-static
ros_cross_compile/qemu/qemu-arm-static
test/dummy_pkg_ros2_py/__init__.py
test/dummy_pkg_ros2_py/setup.py
test/dummy_pkg_ros2_py/dummy_pkg_ros2_py/__init__.py
ros_cross_compile-0.10.0.dist-info/LICENSE
ros_cross_compile-0.10.0.dist-info/METADATA
ros_cross_compile-0.10.0.dist-info/WHEEL
ros_cross_compile-0.10.0.dist-info/entry_points.txt
ros_cross_compile-0.10.0.dist-info/top_level.txt
ros_cross_compile-0.10.0.dist-info/zip-safe
ros_cross_compile-0.10.0.dist-info/RECORD
