Metadata-Version: 2.1
Name: ros-cross-compile
Version: 0.10.0
Summary: A tool to build ROS workspaces for various target architectures and platforms.
Home-page: https://github.com/ros-tooling/cross_compile
Download-URL: https://github.com/ros-tooling/cross_compile/releases
Author: ROS Tooling Working Group
Author-email: ros-tooling@googlegroups.com
Maintainer: ROS Tooling Working Group
Maintainer-email: ros-tooling@googlegroups.com
License: Apache License, Version 2.0
Keywords: ROS,ROS2
Classifier: Development Status :: 4 - Beta
Classifier: Environment :: Console
Classifier: Intended Audience :: Developers
Classifier: License :: OSI Approved :: Apache Software License
Classifier: Programming Language :: Python :: 3.7
Classifier: Programming Language :: Python :: 3.8
Classifier: Topic :: Software Development
Requires-Python: >=3.7
License-File: LICENSE
Requires-Dist: docker (<3,>=2)
Requires-Dist: setuptools
